agent_link/.env.template
agent_link/.git
agent_link/.gitignore
agent_link/.gitmodules
agent_link/.vscode/settings.json
agent_link/CODEOWNERS
agent_link/README.md
agent_link/__devmode__.py
agent_link/__init__.py
agent_link/agent/__base__.py
agent_link/agent/costumer_service/data/company_details.json
agent_link/agent/costumer_service/node.py
agent_link/agent/costumer_service/response.mp3
agent_link/agent/developer/__init__.py
agent_link/agent/developer/node.py
agent_link/agent_link/.env.template
agent_link/agent_link/.git
agent_link/agent_link/.gitignore
agent_link/agent_link/.gitmodules
agent_link/agent_link/.vscode/settings.json
agent_link/agent_link/CODEOWNERS
agent_link/agent_link/__devmode__.py
agent_link/agent_link/agent/__base__.py
agent_link/agent_link/agent/costumer_service/data/company_details.json
agent_link/agent_link/agent/costumer_service/node.py
agent_link/agent_link/agent/costumer_service/response.mp3
agent_link/agent_link/agent/developer/__init__.py
agent_link/agent_link/agent/developer/node.py
agent_link/agent_link/app/.gitignore
agent_link/agent_link/app/build/.import
agent_link/agent_link/app/build/css/styles.css
agent_link/agent_link/app/build/css/xterm.css
agent_link/agent_link/app/build/index.html
agent_link/agent_link/app/build/public/icon_128x128.png
agent_link/agent_link/app/build/public/icon_128x128@2x.png
agent_link/agent_link/app/build/public/icon_16x16.png
agent_link/agent_link/app/build/public/icon_16x16@2x.png
agent_link/agent_link/app/build/public/icon_256x256.png
agent_link/agent_link/app/build/public/icon_256x256@2x.png
agent_link/agent_link/app/build/public/icon_32x32.png
agent_link/agent_link/app/build/public/icon_32x32@2x.png
agent_link/agent_link/app/build/public/icon_512x512.png
agent_link/agent_link/app/build/public/icon_512x512@2x.png
agent_link/agent_link/app/index.html
agent_link/agent_link/app/package-lock.json
agent_link/agent_link/app/package.json
agent_link/agent_link/archive/WARNING.md
agent_link-0.1.2.dist-info/METADATA
agent_link-0.1.2.dist-info/WHEEL
agent_link-0.1.2.dist-info/RECORD
